{
"name": "asterisk",
"sources": [
{
"name": "Thin",
"layerName": "F91D9E91-C1BC-4259-B0D8-112C0CBA2B8E",
"location": {
"Weight": 100
}
},
{
"name": "Regular",
"layerName": "m003"
},
{
"name": "Black",
"layerName": "957254E3-B7AD-4837-9092-D4428001DE8E",
"location": {
"Weight": 900
}
}
],
"layers": {
"957254E3-B7AD-4837-9092-D4428001DE8E": {
"glyph": {
"path": {
"contours": [
{
"points": [
{
"x": 140,
"y": 373
},
{
"x": 200,
"y": 489
},
{
"x": 260,
"y": 373
},
{
"x": 333,
"y": 428
},
{
"x": 242,
"y": 519
},
{
"x": 369,
"y": 539
},
{
"x": 342,
"y": 629
},
{
"x": 226,
"y": 570
},
{
"x": 246,
"y": 697
},
{
"x": 154,
"y": 697
},
{
"x": 174,
"y": 570
},
{
"x": 58,
"y": 629
},
{
"x": 31,
"y": 539
},
{
"x": 158,
"y": 519
},
{
"x": 67,
"y": 428
}
],
"isClosed": true
}
]
},
"xAdvance": 400
}
},
"F91D9E91-C1BC-4259-B0D8-112C0CBA2B8E": {
"glyph": {
"path": {
"contours": [
{
"points": [
{
"x": 99,
"y": 417
},
{
"x": 184,
"y": 532
},
{
"x": 270,
"y": 417
},
{
"x": 280,
"y": 424
},
{
"x": 195,
"y": 540
},
{
"x": 331,
"y": 587
},
{
"x": 328,
"y": 598
},
{
"x": 191,
"y": 553
},
{
"x": 191,
"y": 697
},
{
"x": 178,
"y": 697
},
{
"x": 177,
"y": 553
},
{
"x": 42,
"y": 598
},
{
"x": 37,
"y": 587
},
{
"x": 173,
"y": 540
},
{
"x": 89,
"y": 424
}
],
"isClosed": true
}
]
},
"xAdvance": 368
}
},
"m003": {
"glyph": {
"path": {
"contours": [
{
"points": [
{
"x": 126,
"y": 395
},
{
"x": 199,
"y": 511
},
{
"x": 272,
"y": 395
},
{
"x": 313,
"y": 426
},
{
"x": 226,
"y": 530
},
{
"x": 357,
"y": 564
},
{
"x": 342,
"y": 614
},
{
"x": 216,
"y": 562
},
{
"x": 225,
"y": 697
},
{
"x": 173,
"y": 697
},
{
"x": 183,
"y": 562
},
{
"x": 57,
"y": 614
},
{
"x": 41,
"y": 564
},
{
"x": 173,
"y": 530
},
{
"x": 86,
"y": 426
}
],
"isClosed": true
}
]
},
"xAdvance": 398
}
}
},
"customData": {
"com.glyphsapp.glyph-color": 1
}
}
